spreadsheet_db/__init__.py
spreadsheet_db-1.3.dist-info/LICENSE
spreadsheet_db-1.3.dist-info/METADATA
spreadsheet_db-1.3.dist-info/WHEEL
spreadsheet_db-1.3.dist-info/top_level.txt
spreadsheet_db-1.3.dist-info/RECORD
