Metadata-Version: 2.1
Name: spreadsheet-db
Version: 1.3
Summary: Simply use Google Spreadsheet as DB in Python.
Home-page: https://github.com/da-huin/spreadsheet_db
Author: JunYeong Park
Author-email: dahuin000@gmail.com
License: MIT
Download-URL: https://github.com/da-huin/spreadsheet_db/archive/master.zip
Platform: UNKNOWN
Classifier: Programming Language :: Python :: 3
